[
  {
    "count": 1,
    "created": "2020-03-07 22:48:14",
    "items": [
      {
        "rating": null,
        "color": [
          228,
          232,
          225
        ],
        "image": "https://images.yumprint.com/p1yumprintqe/qE1ThA_rRZKi7DSFYaJfzdgWluD0SzbNjHlQI7p2btcEEUzEEH3ANtoKVZAorol-",
        "mine": false,
        "link": "http://recipes.carlosvelez.net/dinner/pork-fajitas/",
        "id": "uOJ",
        "title": "Pork Fajitas",
        "remove": false,
        "source": "recipes.carlosvelez.net",
        "health": null,
        "trySoonId": "bYV",
        "save": true,
        "type": "recipe",
        "ingredient": [
          "2 Pork Chops",
          "1 Red Pepper",
          "1/2 Red Onion",
          "1 Avocado",
          "1 Lime",
          "4 Tbsp Greek Yogurt",
          "1 Tomato",
          "1/2 cup chopped cilantro"
        ],
        "method": []
      }
    ],
    "title": "Try Soon",
    "id": "trysoon-5w",
    "start": "https://api.yumprint.com/feeds/trysoon-5w/",
    "canRemoveItem": false,
    "trysoon": false
  },
  {
    "canCreateRecipe": false,
    "canCreateCookbook": false,
    "id": "cookbook-oZ_",
    "cookbookId": "oZ_",
    "count": 6,
    "title": "Original Recipes",
    "items": [
      {
        "rating": 4.0,
        "parent": "oZ_",
        "color": [
          224,
          230,
          230
        ],
        "image": "https://images.yumprint.com/p1yumprintcm/cmPoO6Kviga8MrLV5jWt5PWw35r6FUpwdIr061bTRRhskX-kISDOQkS0DcILdWdY",
        "link": "http://recipes.carlosvelez.net/dessert/peanut-butter-chocodilla/",
        "id": "o0u",
        "change": false,
        "title": "Peanut Butter Chocodilla",
        "linkid": "xoB",
        "modified": "2013-03-26 20:27:39",
        "remove": false,
        "source": "recipes.carlosvelez.net",
        "health": 0.41289947800668864,
        "save": true,
        "type": "recipe",
        "ingredient": [
          "2 Fluffy white corn tortillas",
          "2 Tbs Peanut butter",
          "1 Tbs Chocolate chips",
          "1 Tbs Honey",
          "4 tsp Butter or ghee divided"
        ],
        "method": [
          "Melt 2 tsp butter or ghee and place 1 tortilla on top",
          "Spread peanut butter on tortilla",
          "Drizzle with honey and add chocolate chips",
          "Allow chocolate chips to melt, then mix with peanut butter using spoon to smear",
          "Place second tortilla on top and continue to toast until bottom tortilla is golden brown",
          "Remove from heat and cut into four triangles",
          "Let melt and flip tortilla and toast other side"
        ]
      },
      {
        "rating": 4.0,
        "parent": "oZ_",
        "color": [
          167,
          158,
          67
        ],
        "image": "https://images.yumprint.com/p1yumprintyd/YDH2X34MJGWD4ENeGZJ84bYqxLt5CQdT9IF5qbBDzGJukxmkHevL3sPejCmUvRuc",
        "link": "http://recipes.carlosvelez.net/dinner/salmon-coconut-milk-bisque/",
        "id": "o0B",
        "change": false,
        "title": "Salmon Coconut Milk Bisque",
        "linkid": "xoE",
        "modified": "2013-03-26 20:38:10",
        "remove": false,
        "source": "recipes.carlosvelez.net",
        "health": 0.11940471050032542,
        "save": true,
        "type": "recipe",
        "ingredient": [
          "2 cloves garlic",
          "1/2 cup roasted red pepper",
          "1 Leek",
          "4 pinches red pepper flakes",
          "2 cups salmon, grilled, separated into bite-sized chunks",
          "1 32 oz can veggie broth, unsalted",
          "1 13.5 oz can Coconut milk",
          "1 tsp smoked paprika",
          "1-2 stalks lemongrass",
          "1/2 cup parsley"
        ],
        "method": [
          "Prepare garlic, roasted red pepper, leeks, grilled salmon and red pepper flakes. Divide into two portions",
          "Saute 1 portion of above ingredients in pot with oil of choice (I used grapeseed oil), about 5 minutes",
          "Add veggie broth, coconut milk to pot and bring to boil.",
          "Reduce heat and simmer for 15 minutes, stirring frequently",
          "Add \u00bd of salmon bits to pot and blend with immersion blender (alternatively use regular blender and put back in pot)",
          "Add lemongrass, paprika, and 2nd portion of prepared garlic, roasted red pepper, leeks, and red pepper flakes",
          "Simmer for 10 minutes, stirring frequently",
          "Add parsley and remaining salmon until heated through",
          "Serve and garnish with parsley and paprika"
        ]
      },
      {
        "rating": 4.0,
        "parent": "oZ_",
        "color": [
          167,
          158,
          67
        ],
        "image": "https://images.yumprint.com/p1yumprintyd/YDH2X34MJGWD4ENeGZJ84bYqxLt5CQdT9IF5qbBDzGJukxmkHevL3sPejCmUvRuc",
        "link": "http://recipes.carlosvelez.net/dinner/salmon-coconut-milk-bisque/",
        "id": "o0a",
        "change": false,
        "title": "Salmon Coconut Milk Bisque",
        "linkid": "xol",
        "modified": "2013-03-26 20:09:04",
        "remove": false,
        "source": "recipes.carlosvelez.net",
        "health": 0.11940471050032542,
        "save": true,
        "type": "recipe",
        "ingredient": [
          "2 cloves garlic",
          "1/2 cup roasted red pepper",
          "1 Leek",
          "4 pinches red pepper flakes",
          "2 cups salmon, grilled, separated into bite-sized chunks",
          "1 32 oz can veggie broth, unsalted",
          "1 13.5 oz can Coconut milk",
          "1 tsp smoked paprika",
          "1-2 stalks lemongrass",
          "1/2 cup parsley"
        ],
        "method": [
          "Prepare garlic, roasted red pepper, leeks, grilled salmon and red pepper flakes. Divide into two portions",
          "Saute 1 portion of above ingredients in pot with oil of choice (I used grapeseed oil), about 5 minutes",
          "Add veggie broth, coconut milk to pot and bring to boil.",
          "Reduce heat and simmer for 15 minutes, stirring frequently",
          "Add \u00bd of salmon bits to pot and blend with immersion blender (alternatively use regular blender and put back in pot)",
          "Add lemongrass, paprika, and 2nd portion of prepared garlic, roasted red pepper, leeks, and red pepper flakes",
          "Simmer for 10 minutes, stirring frequently",
          "Add parsley and remaining salmon until heated through",
          "Serve and garnish with parsley and paprika"
        ]
      },
      {
        "rating": 4.0,
        "parent": "oZ_",
        "color": [
          43,
          40,
          33
        ],
        "image": "https://images.yumprint.com/p1yumprintdn/DNqKcRy54ifdHVdOH_ueHKqcFXL1OGjRhmhTU9lYarXLjYZzOmEy55WsDo6rU0ij",
        "link": "http://recipes.carlosvelez.net/dessert/sweet-potato-brownies/",
        "id": "o0A",
        "change": false,
        "title": "Sweet Potato Brownies",
        "linkid": "xoC",
        "modified": "2013-03-26 20:36:33",
        "remove": false,
        "source": "recipes.carlosvelez.net",
        "health": 0.26275745039448906,
        "save": true,
        "type": "recipe",
        "ingredient": [
          "4 tablespoons (1/2 stick) unsalted butter",
          "2/3 cup natural unsweetened cocoa powder",
          "1/2 cup whole-wheat pastry flour",
          "1/4 teaspoon baking powder",
          "1/8 teaspoon salt",
          "1/2 cup white sugar",
          "1/2 cup brown sugar",
          "2/3 cup sweet potato puree(about one small potato)",
          "1 large egg",
          "1 1/2 teaspoons vanilla extract"
        ],
        "method": [
          "Heat oven to 350 degrees. Butter an 8-inch square pan; set aside. In a medium saucepan over low heat, melt butter. Remove pan from heat, and stir in cocoa. Let cool slightly.",
          "Meanwhile, in a small bowl, whisk together flour, baking powder, and salt, then stir in sugar and sweet-potato puree, then egg. Add vanilla to cocoa mixture.",
          "Add flour mixture to cocoa mixture and stir until no traces of flour remain. Spoon into prepared pan; smooth the top. Bake until surface of brownies looks barely dry and a knife inserted 2\" from the edge comes out with a few moist crumbs, about 20 minutes.",
          "Technically you should probably let them cool to room temperature before serving, but I recommend using a plastic knife to cut them if you want to cheat and cut while still warm! (necessary if eaten with ice cream)."
        ]
      },
      {
        "rating": 4.0,
        "parent": "oZ_",
        "color": [
          43,
          40,
          33
        ],
        "image": "https://images.yumprint.com/p1yumprintdn/DNqKcRy54ifdHVdOH_ueHKqcFXL1OGjRhmhTU9lYarXLjYZzOmEy55WsDo6rU0ij",
        "link": "http://recipes.carlosvelez.net/dessert/sweet-potato-brownies/",
        "id": "o0c",
        "change": false,
        "title": "Sweet Potato Brownies",
        "linkid": "xoo",
        "modified": "2013-03-26 20:10:46",
        "remove": false,
        "source": "recipes.carlosvelez.net",
        "health": 0.26275745039448906,
        "save": true,
        "type": "recipe",
        "ingredient": [
          "4 tablespoons (1/2 stick) unsalted butter",
          "2/3 cup natural unsweetened cocoa powder",
          "1/2 cup whole-wheat pastry flour",
          "1/4 teaspoon baking powder",
          "1/8 teaspoon salt",
          "1/2 cup white sugar",
          "1/2 cup brown sugar",
          "2/3 cup sweet potato puree(about one small potato)",
          "1 large egg",
          "1 1/2 teaspoons vanilla extract"
        ],
        "method": [
          "Heat oven to 350 degrees. Butter an 8-inch square pan; set aside. In a medium saucepan over low heat, melt butter. Remove pan from heat, and stir in cocoa. Let cool slightly.",
          "Meanwhile, in a small bowl, whisk together flour, baking powder, and salt, then stir in sugar and sweet-potato puree, then egg. Add vanilla to cocoa mixture.",
          "Add flour mixture to cocoa mixture and stir until no traces of flour remain. Spoon into prepared pan; smooth the top. Bake until surface of brownies looks barely dry and a knife inserted 2\" from the edge comes out with a few moist crumbs, about 20 minutes.",
          "Technically you should probably let them cool to room temperature before serving, but I recommend using a plastic knife to cut them if you want to cheat and cut while still warm! (necessary if eaten with ice cream)."
        ]
      },
      {
        "rating": 4.0,
        "parent": "oZ_",
        "color": [
          43,
          40,
          33
        ],
        "image": "https://images.yumprint.com/p1yumprintdn/DNqKcRy54ifdHVdOH_ueHKqcFXL1OGjRhmhTU9lYarXLjYZzOmEy55WsDo6rU0ij",
        "link": "http://recipes.carlosvelez.net/dessert/sweet-potato-brownies/",
        "id": "o0t",
        "change": false,
        "title": "Sweet Potato Brownies",
        "linkid": "xoA",
        "modified": "2013-03-26 20:27:01",
        "remove": false,
        "source": "recipes.carlosvelez.net",
        "health": 0.26275745039448906,
        "save": true,
        "type": "recipe",
        "ingredient": [
          "4 tablespoons (1/2 stick) unsalted butter",
          "2/3 cup natural unsweetened cocoa powder",
          "1/2 cup whole-wheat pastry flour",
          "1/4 teaspoon baking powder",
          "1/8 teaspoon salt",
          "1/2 cup white sugar",
          "1/2 cup brown sugar",
          "2/3 cup sweet potato puree(about one small potato)",
          "1 large egg",
          "1 1/2 teaspoons vanilla extract"
        ],
        "method": [
          "Heat oven to 350 degrees. Butter an 8-inch square pan; set aside. In a medium saucepan over low heat, melt butter. Remove pan from heat, and stir in cocoa. Let cool slightly.",
          "Meanwhile, in a small bowl, whisk together flour, baking powder, and salt, then stir in sugar and sweet-potato puree, then egg. Add vanilla to cocoa mixture.",
          "Add flour mixture to cocoa mixture and stir until no traces of flour remain. Spoon into prepared pan; smooth the top. Bake until surface of brownies looks barely dry and a knife inserted 2\" from the edge comes out with a few moist crumbs, about 20 minutes.",
          "Technically you should probably let them cool to room temperature before serving, but I recommend using a plastic knife to cut them if you want to cheat and cut while still warm! (necessary if eaten with ice cream)."
        ]
      }
    ],
    "created": "2020-03-07 22:48:17",
    "start": "https://api.yumprint.com/feeds/cookbook-oZ_/",
    "canRemoveItem": false,
    "type": "feed"
  }
]